antlr/__init__.py
antlr/throwing_error_listener.py
antlr/thrown_exception.py
vba_linter/__init__.py
vba_linter/__main__.py
vba_linter/linter.py
vba_linter/rule_directory.py
vba_linter/rules/__init__.py
vba_linter/rules/e101.py
vba_linter/rules/e999.py
vba_linter/rules/rule_base.py
vba_linter/rules/token_after_base.py
vba_linter/rules/token_before_base.py
vba_linter/rules/token_between_base.py
vba_linter/rules/w191.py
vba_linter/rules/w201.py
vba_linter/rules/w291.py
vba_linter/rules/w391.py
vba_linter/rules/w500.py
vba_linter/rules/w501.py
vba_linter-0.0.4.dist-info/LICENSE
vba_linter-0.0.4.dist-info/METADATA
vba_linter-0.0.4.dist-info/WHEEL
vba_linter-0.0.4.dist-info/top_level.txt
vba_linter-0.0.4.dist-info/RECORD
