Metadata-Version: 2.1
Name: vba-linter
Version: 0.0.4
Summary: Lint VBA code.
Author-email: Kevin Nowaczyk <beakerboy99@yahoo.com>
Project-URL: Homepage, https://github.com/Beakerboy/VBA-Linter
Project-URL: Bug Tracker, https://github.com/Beakerboy/VBA-Linter/issues
Classifier: Programming Language :: Python :: 3
Classifier: License :: OSI Approved :: MIT License
Classifier: Operating System :: OS Independent
Requires-Python: >=3.7
License-File: LICENSE
Requires-Dist: PyYAML
Requires-Dist: antlr4-python3-runtime
Requires-Dist: antlr4-tools
Requires-Dist: antlr4-vba
Provides-Extra: tests
Requires-Dist: mypy ; extra == 'tests'
Requires-Dist: pytest ; extra == 'tests'
Requires-Dist: pytest-cov ; extra == 'tests'
Requires-Dist: pytest-mock ; extra == 'tests'
Requires-Dist: coveralls ; extra == 'tests'
Requires-Dist: pep8-naming ; extra == 'tests'
Requires-Dist: flake8-annotations ; extra == 'tests'
